{
  "version": "1.0.3",
  "keycodes": [
    { "id": "KC_NO", "label": "No", "short": "No", "group": "special", "type": "basic", "code": 0, "aliases": ["NONE"] },
    { "id": "KC_TRNS", "label": "Transparent", "short": "Trns", "group": "special", "type": "basic", "code": 1, "aliases": ["TRANS"] },

    { "id": "KC_A", "label": "A", "short": "A", "group": "alpha", "type": "basic", "code": 4 },
    { "id": "KC_B", "label": "B", "short": "B", "group": "alpha", "type": "basic", "code": 5 },
    { "id": "KC_C", "label": "C", "short": "C", "group": "alpha", "type": "basic", "code": 6 },
    { "id": "KC_D", "label": "D", "short": "D", "group": "alpha", "type": "basic", "code": 7 },
    { "id": "KC_E", "label": "E", "short": "E", "group": "alpha", "type": "basic", "code": 8 },
    { "id": "KC_F", "label": "F", "short": "F", "group": "alpha", "type": "basic", "code": 9 },
    { "id": "KC_G", "label": "G", "short": "G", "group": "alpha", "type": "basic", "code": 10 },
    { "id": "KC_H", "label": "H", "short": "H", "group": "alpha", "type": "basic", "code": 11 },
    { "id": "KC_I", "label": "I", "short": "I", "group": "alpha", "type": "basic", "code": 12 },
    { "id": "KC_J", "label": "J", "short": "J", "group": "alpha", "type": "basic", "code": 13 },
    { "id": "KC_K", "label": "K", "short": "K", "group": "alpha", "type": "basic", "code": 14 },
    { "id": "KC_L", "label": "L", "short": "L", "group": "alpha", "type": "basic", "code": 15 },
    { "id": "KC_M", "label": "M", "short": "M", "group": "alpha", "type": "basic", "code": 16 },
    { "id": "KC_N", "label": "N", "short": "N", "group": "alpha", "type": "basic", "code": 17 },
    { "id": "KC_O", "label": "O", "short": "O", "group": "alpha", "type": "basic", "code": 18 },
    { "id": "KC_P", "label": "P", "short": "P", "group": "alpha", "type": "basic", "code": 19 },
    { "id": "KC_Q", "label": "Q", "short": "Q", "group": "alpha", "type": "basic", "code": 20 },
    { "id": "KC_R", "label": "R", "short": "R", "group": "alpha", "type": "basic", "code": 21 },
    { "id": "KC_S", "label": "S", "short": "S", "group": "alpha", "type": "basic", "code": 22 },
    { "id": "KC_T", "label": "T", "short": "T", "group": "alpha", "type": "basic", "code": 23 },
    { "id": "KC_U", "label": "U", "short": "U", "group": "alpha", "type": "basic", "code": 24 },
    { "id": "KC_V", "label": "V", "short": "V", "group": "alpha", "type": "basic", "code": 25 },
    { "id": "KC_W", "label": "W", "short": "W", "group": "alpha", "type": "basic", "code": 26 },
    { "id": "KC_X", "label": "X", "short": "X", "group": "alpha", "type": "basic", "code": 27 },
    { "id": "KC_Y", "label": "Y", "short": "Y", "group": "alpha", "type": "basic", "code": 28 },
    { "id": "KC_Z", "label": "Z", "short": "Z", "group": "alpha", "type": "basic", "code": 29 },

    { "id": "KC_1", "label": "1", "short": "1", "group": "number", "type": "basic", "code": 30, "aliases": ["DIGIT_1"] },
    { "id": "KC_2", "label": "2", "short": "2", "group": "number", "type": "basic", "code": 31, "aliases": ["DIGIT_2"] },
    { "id": "KC_3", "label": "3", "short": "3", "group": "number", "type": "basic", "code": 32, "aliases": ["DIGIT_3"] },
    { "id": "KC_4", "label": "4", "short": "4", "group": "number", "type": "basic", "code": 33, "aliases": ["DIGIT_4"] },
    { "id": "KC_5", "label": "5", "short": "5", "group": "number", "type": "basic", "code": 34, "aliases": ["DIGIT_5"] },
    { "id": "KC_6", "label": "6", "short": "6", "group": "number", "type": "basic", "code": 35, "aliases": ["DIGIT_6"] },
    { "id": "KC_7", "label": "7", "short": "7", "group": "number", "type": "basic", "code": 36, "aliases": ["DIGIT_7"] },
    { "id": "KC_8", "label": "8", "short": "8", "group": "number", "type": "basic", "code": 37, "aliases": ["DIGIT_8"] },
    { "id": "KC_9", "label": "9", "short": "9", "group": "number", "type": "basic", "code": 38, "aliases": ["DIGIT_9"] },
    { "id": "KC_0", "label": "0", "short": "0", "group": "number", "type": "basic", "code": 39, "aliases": ["DIGIT_0"] },

    { "id": "KC_ENTER", "label": "Enter", "short": "Ent", "group": "control", "type": "basic", "code": 40, "aliases": ["ENTER"] },
    { "id": "KC_ESC", "label": "Esc", "short": "Esc", "group": "control", "type": "basic", "code": 41, "aliases": ["ESC"] },
    { "id": "KC_BSPC", "label": "Backspace", "short": "Bksp", "group": "control", "type": "basic", "code": 42, "aliases": ["BACKSPACE"] },
    { "id": "KC_TAB", "label": "Tab", "short": "Tab", "group": "control", "type": "basic", "code": 43, "aliases": ["TAB"] },
    { "id": "KC_SPACE", "label": "Space", "short": "Spc", "group": "control", "type": "basic", "code": 44, "aliases": ["SPACE"] },
    { "id": "KC_CAPS", "label": "Caps", "short": "Caps", "group": "control", "type": "basic", "code": 57, "aliases": ["CAPSLOCK"] },

    { "id": "KC_MINUS", "label": "-", "short": "-", "group": "punc", "type": "basic", "code": 45, "aliases": ["MINUS"] },
    { "id": "KC_EQUAL", "label": "=", "short": "=", "group": "punc", "type": "basic", "code": 46, "aliases": ["EQUALS"] },
    { "id": "KC_LBRC", "label": "[", "short": "[", "group": "punc", "type": "basic", "code": 47, "aliases": ["LBRACKET"] },
    { "id": "KC_RBRC", "label": "]", "short": "]", "group": "punc", "type": "basic", "code": 48, "aliases": ["RBRACKET"] },
    { "id": "KC_BSLS", "label": "\\\\", "short": "\\\\", "group": "punc", "type": "basic", "code": 49, "aliases": ["BACKSLASH"] },
    { "id": "KC_SCLN", "label": ";", "short": ";", "group": "punc", "type": "basic", "code": 51, "aliases": ["SEMICOLON"] },
    { "id": "KC_QUOT", "label": "'", "short": "'", "group": "punc", "type": "basic", "code": 52, "aliases": ["QUOTE"] },
    { "id": "KC_GRV", "label": "`", "short": "`", "group": "punc", "type": "basic", "code": 53, "aliases": ["BACKTICK"] },
    { "id": "KC_COMM", "label": ",", "short": ",", "group": "punc", "type": "basic", "code": 54, "aliases": ["COMMA"] },
    { "id": "KC_DOT", "label": ".", "short": ".", "group": "punc", "type": "basic", "code": 55, "aliases": ["PERIOD"] },
    { "id": "KC_SLSH", "label": "/", "short": "/", "group": "punc", "type": "basic", "code": 56, "aliases": ["SLASH"] },
    { "id": "KC_NONUS_HASH", "label": "NonUS #", "short": "N#", "group": "punc", "type": "basic", "code": 50, "aliases": ["NONUS_HASH"] },
    { "id": "KC_NUBS", "label": "NonUS \\\\", "short": "N\\\\", "group": "punc", "type": "basic", "code": 100, "aliases": ["NONUS_BSLASH"] },

    { "id": "KC_LCTL", "label": "Left Ctrl", "short": "LCtl", "group": "mod", "type": "basic", "code": 224, "aliases": ["LCTRL"] },
    { "id": "KC_LSFT", "label": "Left Shift", "short": "LSft", "group": "mod", "type": "basic", "code": 225, "aliases": ["LSHIFT"] },
    { "id": "KC_LALT", "label": "Left Alt", "short": "LAlt", "group": "mod", "type": "basic", "code": 226, "aliases": ["LALT"] },
    { "id": "KC_LGUI", "label": "Left Meta", "short": "LGui", "group": "mod", "type": "basic", "code": 227, "aliases": ["LGUI"] },
    { "id": "KC_RCTL", "label": "Right Ctrl", "short": "RCtl", "group": "mod", "type": "basic", "code": 228, "aliases": ["RCTRL"] },
    { "id": "KC_RSFT", "label": "Right Shift", "short": "RSft", "group": "mod", "type": "basic", "code": 229, "aliases": ["RSHIFT"] },
    { "id": "KC_RALT", "label": "Right Alt", "short": "RAlt", "group": "mod", "type": "basic", "code": 230, "aliases": ["RALT"] },
    { "id": "KC_RGUI", "label": "Right Meta", "short": "RGui", "group": "mod", "type": "basic", "code": 231, "aliases": ["RGUI"] },

    { "id": "KC_UP", "label": "Up", "short": "↑", "group": "nav", "type": "basic", "code": 82, "aliases": ["ARROW_UP"] },
    { "id": "KC_DOWN", "label": "Down", "short": "↓", "group": "nav", "type": "basic", "code": 81, "aliases": ["ARROW_DOWN"] },
    { "id": "KC_LEFT", "label": "Left", "short": "←", "group": "nav", "type": "basic", "code": 80, "aliases": ["ARROW_LEFT"] },
    { "id": "KC_RIGHT", "label": "Right", "short": "→", "group": "nav", "type": "basic", "code": 79, "aliases": ["ARROW_RIGHT"] },
    { "id": "KC_HOME", "label": "Home", "short": "Home", "group": "nav", "type": "basic", "code": 74, "aliases": ["HOME"] },
    { "id": "KC_END", "label": "End", "short": "End", "group": "nav", "type": "basic", "code": 77, "aliases": ["END"] },
    { "id": "KC_PGUP", "label": "PgUp", "short": "PgUp", "group": "nav", "type": "basic", "code": 75, "aliases": ["PGUP"] },
    { "id": "KC_PGDN", "label": "PgDn", "short": "PgDn", "group": "nav", "type": "basic", "code": 78, "aliases": ["PGDN"] },
    { "id": "KC_INS", "label": "Insert", "short": "Ins", "group": "nav", "type": "basic", "code": 73, "aliases": ["INSERT"] },
    { "id": "KC_DEL", "label": "Delete", "short": "Del", "group": "nav", "type": "basic", "code": 76, "aliases": ["DELETE"] },

    { "id": "QK_TO", "label": "TO", "short": "TO", "group": "layer", "type": "layer", "base": 20992, "params": ["layer"] },
    { "id": "QK_MO", "label": "MO", "short": "MO", "group": "layer", "type": "layer", "base": 21024, "params": ["layer"] },
    { "id": "QK_DF", "label": "DF", "short": "DF", "group": "layer", "type": "layer", "base": 21056, "params": ["layer"] },
    { "id": "QK_TG", "label": "TG", "short": "TG", "group": "layer", "type": "layer", "base": 21088, "params": ["layer"] },
    { "id": "QK_OSL", "label": "OSL", "short": "OSL", "group": "layer", "type": "layer", "base": 20736, "params": ["layer"] },
    { "id": "QK_LT", "label": "LT", "short": "LT", "group": "layerTap", "type": "layerTap", "base": 16384, "params": ["layer", "tap"] },
    { "id": "QK_MT", "label": "MT", "short": "MT", "group": "modTap", "type": "modTap", "base": 24576, "params": ["mod", "tap"] },

    { "id": "QK_ONE_SHOT_MOD_LCTL", "label": "OSM Ctrl", "short": "OMCtl", "group": "oneshot", "type": "basic", "code": 21776 },
    { "id": "QK_ONE_SHOT_MOD_LSFT", "label": "OSM Shift", "short": "OMSft", "group": "oneshot", "type": "basic", "code": 21777 },
    { "id": "QK_ONE_SHOT_MOD_LALT", "label": "OSM Alt", "short": "OMAlt", "group": "oneshot", "type": "basic", "code": 21778 },
    { "id": "QK_ONE_SHOT_MOD_LGUI", "label": "OSM Gui", "short": "OMGui", "group": "oneshot", "type": "basic", "code": 21779 },
    { "id": "QK_ONE_SHOT_MOD_RCTL", "label": "OSM RCtrl", "short": "OMRCt", "group": "oneshot", "type": "basic", "code": 21780 },
    { "id": "QK_ONE_SHOT_MOD_RSFT", "label": "OSM RShift", "short": "OMRSf", "group": "oneshot", "type": "basic", "code": 21781 },
    { "id": "QK_ONE_SHOT_MOD_RALT", "label": "OSM RAlt", "short": "OMRAl", "group": "oneshot", "type": "basic", "code": 21782 },
    { "id": "QK_ONE_SHOT_MOD_RGUI", "label": "OSM RGui", "short": "OMRGu", "group": "oneshot", "type": "basic", "code": 21783 },

    { "id": "QK_RGB_TOG", "label": "RGB Toggle", "short": "RGB", "group": "rgb", "type": "basic", "code": 32513, "requires": ["rgb"] },
    { "id": "QK_RGB_HUI", "label": "RGB Hue+", "short": "Hue+", "group": "rgb", "type": "basic", "code": 32514, "requires": ["rgb"] },
    { "id": "QK_RGB_HUD", "label": "RGB Hue-", "short": "Hue-", "group": "rgb", "type": "basic", "code": 32515, "requires": ["rgb"] },
    { "id": "QK_RGB_SAI", "label": "RGB Sat+", "short": "Sat+", "group": "rgb", "type": "basic", "code": 32516, "requires": ["rgb"] },
    { "id": "QK_RGB_SAD", "label": "RGB Sat-", "short": "Sat-", "group": "rgb", "type": "basic", "code": 32517, "requires": ["rgb"] },
    { "id": "QK_RGB_VAI", "label": "RGB Val+", "short": "Val+", "group": "rgb", "type": "basic", "code": 32518, "requires": ["rgb"] },
    { "id": "QK_RGB_VAD", "label": "RGB Val-", "short": "Val-", "group": "rgb", "type": "basic", "code": 32519, "requires": ["rgb"] },
    { "id": "QK_RGB_MOD", "label": "RGB Mode+", "short": "RMd+", "group": "rgb", "type": "basic", "code": 32520, "requires": ["rgb"] },
    { "id": "QK_RGB_RMOD", "label": "RGB Mode-", "short": "RMd-", "group": "rgb", "type": "basic", "code": 32521, "requires": ["rgb"] },
    { "id": "QK_RGB_SPI", "label": "RGB Speed+", "short": "RSp+", "group": "rgb", "type": "basic", "code": 32522, "requires": ["rgb"] },
    { "id": "QK_RGB_SPD", "label": "RGB Speed-", "short": "RSp-", "group": "rgb", "type": "basic", "code": 32523, "requires": ["rgb"] },
    { "id": "QK_BL_TOGG", "label": "Backlight Toggle", "short": "BL", "group": "backlight", "type": "basic", "code": 30720, "requires": ["backlight"] },
    { "id": "QK_BL_ON", "label": "Backlight On", "short": "BLOn", "group": "backlight", "type": "basic", "code": 30721, "requires": ["backlight"] },
    { "id": "QK_BL_OFF", "label": "Backlight Off", "short": "BLOf", "group": "backlight", "type": "basic", "code": 30722, "requires": ["backlight"] },
    { "id": "QK_BL_UP", "label": "Backlight+", "short": "BL+", "group": "backlight", "type": "basic", "code": 30724, "requires": ["backlight"] },
    { "id": "QK_BL_DOWN", "label": "Backlight-", "short": "BL-", "group": "backlight", "type": "basic", "code": 30725, "requires": ["backlight"] },
    { "id": "QK_BL_STEP", "label": "Backlight Step", "short": "BLSt", "group": "backlight", "type": "basic", "code": 30726, "requires": ["backlight"] },

    { "id": "KC_F1", "label": "F1", "short": "F1", "group": "function", "type": "basic", "code": 58, "aliases": ["F1"] },
    { "id": "KC_F2", "label": "F2", "short": "F2", "group": "function", "type": "basic", "code": 59, "aliases": ["F2"] },
    { "id": "KC_F3", "label": "F3", "short": "F3", "group": "function", "type": "basic", "code": 60, "aliases": ["F3"] },
    { "id": "KC_F4", "label": "F4", "short": "F4", "group": "function", "type": "basic", "code": 61, "aliases": ["F4"] },
    { "id": "KC_F5", "label": "F5", "short": "F5", "group": "function", "type": "basic", "code": 62, "aliases": ["F5"] },
    { "id": "KC_F6", "label": "F6", "short": "F6", "group": "function", "type": "basic", "code": 63, "aliases": ["F6"] },
    { "id": "KC_F7", "label": "F7", "short": "F7", "group": "function", "type": "basic", "code": 64, "aliases": ["F7"] },
    { "id": "KC_F8", "label": "F8", "short": "F8", "group": "function", "type": "basic", "code": 65, "aliases": ["F8"] },
    { "id": "KC_F9", "label": "F9", "short": "F9", "group": "function", "type": "basic", "code": 66, "aliases": ["F9"] },
    { "id": "KC_F10", "label": "F10", "short": "F10", "group": "function", "type": "basic", "code": 67, "aliases": ["F10"] },
    { "id": "KC_F11", "label": "F11", "short": "F11", "group": "function", "type": "basic", "code": 68, "aliases": ["F11"] },
    { "id": "KC_F12", "label": "F12", "short": "F12", "group": "function", "type": "basic", "code": 69, "aliases": ["F12"] },
    { "id": "KC_F13", "label": "F13", "short": "F13", "group": "function", "type": "basic", "code": 104, "aliases": ["F13"] },
    { "id": "KC_F14", "label": "F14", "short": "F14", "group": "function", "type": "basic", "code": 105, "aliases": ["F14"] },
    { "id": "KC_F15", "label": "F15", "short": "F15", "group": "function", "type": "basic", "code": 106, "aliases": ["F15"] },
    { "id": "KC_F16", "label": "F16", "short": "F16", "group": "function", "type": "basic", "code": 107, "aliases": ["F16"] },
    { "id": "KC_F17", "label": "F17", "short": "F17", "group": "function", "type": "basic", "code": 108, "aliases": ["F17"] },
    { "id": "KC_F18", "label": "F18", "short": "F18", "group": "function", "type": "basic", "code": 109, "aliases": ["F18"] },
    { "id": "KC_F19", "label": "F19", "short": "F19", "group": "function", "type": "basic", "code": 110, "aliases": ["F19"] },
    { "id": "KC_F20", "label": "F20", "short": "F20", "group": "function", "type": "basic", "code": 111, "aliases": ["F20"] },
    { "id": "KC_F21", "label": "F21", "short": "F21", "group": "function", "type": "basic", "code": 112, "aliases": ["F21"] },
    { "id": "KC_F22", "label": "F22", "short": "F22", "group": "function", "type": "basic", "code": 113, "aliases": ["F22"] },
    { "id": "KC_F23", "label": "F23", "short": "F23", "group": "function", "type": "basic", "code": 114, "aliases": ["F23"] },
    { "id": "KC_F24", "label": "F24", "short": "F24", "group": "function", "type": "basic", "code": 115, "aliases": ["F24"] },

    { "id": "KC_P1", "label": "KP 1", "short": "P1", "group": "numpad", "type": "basic", "code": 89, "aliases": ["NUMPAD_1"] },
    { "id": "KC_P2", "label": "KP 2", "short": "P2", "group": "numpad", "type": "basic", "code": 90, "aliases": ["NUMPAD_2"] },
    { "id": "KC_P3", "label": "KP 3", "short": "P3", "group": "numpad", "type": "basic", "code": 91, "aliases": ["NUMPAD_3"] },
    { "id": "KC_P4", "label": "KP 4", "short": "P4", "group": "numpad", "type": "basic", "code": 92, "aliases": ["NUMPAD_4"] },
    { "id": "KC_P5", "label": "KP 5", "short": "P5", "group": "numpad", "type": "basic", "code": 93, "aliases": ["NUMPAD_5"] },
    { "id": "KC_P6", "label": "KP 6", "short": "P6", "group": "numpad", "type": "basic", "code": 94, "aliases": ["NUMPAD_6"] },
    { "id": "KC_P7", "label": "KP 7", "short": "P7", "group": "numpad", "type": "basic", "code": 95, "aliases": ["NUMPAD_7"] },
    { "id": "KC_P8", "label": "KP 8", "short": "P8", "group": "numpad", "type": "basic", "code": 96, "aliases": ["NUMPAD_8"] },
    { "id": "KC_P9", "label": "KP 9", "short": "P9", "group": "numpad", "type": "basic", "code": 97, "aliases": ["NUMPAD_9"] },
    { "id": "KC_P0", "label": "KP 0", "short": "P0", "group": "numpad", "type": "basic", "code": 98, "aliases": ["NUMPAD_0"] },
    { "id": "KC_PDOT", "label": "KP .", "short": "P.", "group": "numpad", "type": "basic", "code": 99, "aliases": ["NUMPAD_DOT"] },
    { "id": "KC_PSLASH", "label": "KP /", "short": "P/", "group": "numpad", "type": "basic", "code": 84, "aliases": ["NUMPAD_SLASH"] },
    { "id": "KC_PAST", "label": "KP *", "short": "P*", "group": "numpad", "type": "basic", "code": 85, "aliases": ["NUMPAD_STAR"] },
    { "id": "KC_PMNS", "label": "KP -", "short": "P-", "group": "numpad", "type": "basic", "code": 86, "aliases": ["NUMPAD_MINUS"] },
    { "id": "KC_PPLS", "label": "KP +", "short": "P+", "group": "numpad", "type": "basic", "code": 87, "aliases": ["NUMPAD_PLUS"] },
    { "id": "KC_PENT", "label": "KP Enter", "short": "PEnt", "group": "numpad", "type": "basic", "code": 88, "aliases": ["NUMPAD_ENTER"] },
    { "id": "KC_NLCK", "label": "Num Lock", "short": "Num", "group": "numpad", "type": "basic", "code": 83, "aliases": ["NUMLOCK"] },
    { "id": "KC_PEQL", "label": "KP =", "short": "P=", "group": "numpad", "type": "basic", "code": 103, "aliases": ["NUMPAD_EQUAL"] },

    { "id": "KC_MUTE", "label": "Mute", "short": "Mut", "group": "media", "type": "basic", "code": 168, "aliases": ["MUTE", "VOLUME_MUTE"] },
    { "id": "KC_VOLU", "label": "Vol+", "short": "Vol+", "group": "media", "type": "basic", "code": 169, "aliases": ["VOLUME_UP"] },
    { "id": "KC_VOLD", "label": "Vol-", "short": "Vol-", "group": "media", "type": "basic", "code": 170, "aliases": ["VOLUME_DOWN"] },
    { "id": "KC_MNXT", "label": "Next", "short": "Nxt", "group": "media", "type": "basic", "code": 171, "aliases": ["MEDIA_NEXT"] },
    { "id": "KC_MPRV", "label": "Prev", "short": "Prv", "group": "media", "type": "basic", "code": 172, "aliases": ["MEDIA_PREV"] },
    { "id": "KC_MSTP", "label": "Stop", "short": "Stop", "group": "media", "type": "basic", "code": 173, "aliases": ["MEDIA_STOP"] },
    { "id": "KC_MPLY", "label": "Play/Pause", "short": "Play", "group": "media", "type": "basic", "code": 174, "aliases": ["MEDIA_PLAY_PAUSE"] },
    { "id": "KC_MSEL", "label": "Media Select", "short": "Sel", "group": "media", "type": "basic", "code": 175, "aliases": ["MEDIA_SELECT"] },
    { "id": "KC_EJCT", "label": "Eject", "short": "Ejct", "group": "media", "type": "basic", "code": 176, "aliases": ["EJECT"] },
    { "id": "KC_MAIL", "label": "Mail", "short": "Mail", "group": "media", "type": "basic", "code": 177 },
    { "id": "KC_CALC", "label": "Calculator", "short": "Calc", "group": "media", "type": "basic", "code": 178 },
    { "id": "KC_MYCM", "label": "My Computer", "short": "Comp", "group": "media", "type": "basic", "code": 179 },
    { "id": "KC_WSCH", "label": "Browser Search", "short": "WebS", "group": "media", "type": "basic", "code": 180 },
    { "id": "KC_WHOM", "label": "Browser Home", "short": "WebH", "group": "media", "type": "basic", "code": 181 },
    { "id": "KC_WBAK", "label": "Browser Back", "short": "Web←", "group": "media", "type": "basic", "code": 182 },
    { "id": "KC_WFWD", "label": "Browser Forward", "short": "Web→", "group": "media", "type": "basic", "code": 183 },
    { "id": "KC_WSTP", "label": "Browser Stop", "short": "WebX", "group": "media", "type": "basic", "code": 184 },
    { "id": "KC_WREF", "label": "Browser Refresh", "short": "WebR", "group": "media", "type": "basic", "code": 185 },
    { "id": "KC_WFAV", "label": "Browser Favorites", "short": "Fav", "group": "media", "type": "basic", "code": 186 },
    { "id": "KC_MFFD", "label": "Media FF", "short": "FFwd", "group": "media", "type": "basic", "code": 187, "aliases": ["MEDIA_FAST_FORWARD"] },
    { "id": "KC_MRWD", "label": "Media RW", "short": "Rwd", "group": "media", "type": "basic", "code": 188, "aliases": ["MEDIA_REWIND"] },
    { "id": "KC_BRIU", "label": "Bright+", "short": "Bri+", "group": "media", "type": "basic", "code": 189, "aliases": ["BRIGHTNESS_UP"] },
    { "id": "KC_BRID", "label": "Bright-", "short": "Bri-", "group": "media", "type": "basic", "code": 190, "aliases": ["BRIGHTNESS_DOWN"] },

    { "id": "KC_MS_U", "label": "Mouse Up", "short": "Ms↑", "group": "mouse", "type": "basic", "code": 205, "aliases": ["MOUSE_UP"] },
    { "id": "KC_MS_D", "label": "Mouse Down", "short": "Ms↓", "group": "mouse", "type": "basic", "code": 206, "aliases": ["MOUSE_DOWN"] },
    { "id": "KC_MS_L", "label": "Mouse Left", "short": "Ms←", "group": "mouse", "type": "basic", "code": 207, "aliases": ["MOUSE_LEFT"] },
    { "id": "KC_MS_R", "label": "Mouse Right", "short": "Ms→", "group": "mouse", "type": "basic", "code": 208, "aliases": ["MOUSE_RIGHT"] },
    { "id": "KC_BTN1", "label": "Mouse Btn 1", "short": "Btn1", "group": "mouse", "type": "basic", "code": 209, "aliases": ["MOUSE_BTN1"] },
    { "id": "KC_BTN2", "label": "Mouse Btn 2", "short": "Btn2", "group": "mouse", "type": "basic", "code": 210, "aliases": ["MOUSE_BTN2"] },
    { "id": "KC_BTN3", "label": "Mouse Btn 3", "short": "Btn3", "group": "mouse", "type": "basic", "code": 211, "aliases": ["MOUSE_BTN3"] },
    { "id": "KC_BTN4", "label": "Mouse Btn 4", "short": "Btn4", "group": "mouse", "type": "basic", "code": 212, "aliases": ["MOUSE_BTN4"] },
    { "id": "KC_BTN5", "label": "Mouse Btn 5", "short": "Btn5", "group": "mouse", "type": "basic", "code": 213, "aliases": ["MOUSE_BTN5"] },
    { "id": "KC_WH_U", "label": "Wheel Up", "short": "Wh↑", "group": "mouse", "type": "basic", "code": 217, "aliases": ["WHEEL_UP"] },
    { "id": "KC_WH_D", "label": "Wheel Down", "short": "Wh↓", "group": "mouse", "type": "basic", "code": 218, "aliases": ["WHEEL_DOWN"] },
    { "id": "KC_WH_L", "label": "Wheel Left", "short": "Wh←", "group": "mouse", "type": "basic", "code": 219, "aliases": ["WHEEL_LEFT"] },
    { "id": "KC_WH_R", "label": "Wheel Right", "short": "Wh→", "group": "mouse", "type": "basic", "code": 220, "aliases": ["WHEEL_RIGHT"] },
    { "id": "KC_ACL0", "label": "Mouse Accel 0", "short": "Acl0", "group": "mouse", "type": "basic", "code": 221, "aliases": ["MOUSE_ACCEL0"] },
    { "id": "KC_ACL1", "label": "Mouse Accel 1", "short": "Acl1", "group": "mouse", "type": "basic", "code": 222, "aliases": ["MOUSE_ACCEL1"] },
    { "id": "KC_ACL2", "label": "Mouse Accel 2", "short": "Acl2", "group": "mouse", "type": "basic", "code": 223, "aliases": ["MOUSE_ACCEL2"] },

    { "id": "QK_AUDIO_ON", "label": "Audio On", "short": "AudOn", "group": "audio", "type": "basic", "code": 24320, "requires": ["audio"] },
    { "id": "QK_AUDIO_OFF", "label": "Audio Off", "short": "AudOf", "group": "audio", "type": "basic", "code": 24321, "requires": ["audio"] },
    { "id": "QK_AUDIO_TOGGLE", "label": "Audio Toggle", "short": "Aud", "group": "audio", "type": "basic", "code": 24322, "requires": ["audio"] },
    { "id": "QK_MUSIC_ON", "label": "Music On", "short": "MusOn", "group": "audio", "type": "basic", "code": 24336, "requires": ["audio"] },
    { "id": "QK_MUSIC_OFF", "label": "Music Off", "short": "MusOf", "group": "audio", "type": "basic", "code": 24337, "requires": ["audio"] },
    { "id": "QK_MUSIC_TOGGLE", "label": "Music Toggle", "short": "Mus", "group": "audio", "type": "basic", "code": 24338, "requires": ["audio"] },

    { "id": "QK_EXECUTE", "label": "Execute", "short": "Exec", "group": "system", "type": "basic", "code": 116 },
    { "id": "QK_HELP", "label": "Help", "short": "Hlp", "group": "system", "type": "basic", "code": 117 },
    { "id": "QK_MENU", "label": "Menu", "short": "Menu", "group": "system", "type": "basic", "code": 118 },
    { "id": "QK_SELECT", "label": "Select", "short": "Sel", "group": "system", "type": "basic", "code": 119 },
    { "id": "QK_STOP", "label": "Stop", "short": "Stop", "group": "system", "type": "basic", "code": 120 },
    { "id": "QK_AGAIN", "label": "Again", "short": "Agn", "group": "system", "type": "basic", "code": 121 },
    { "id": "QK_UNDO", "label": "Undo", "short": "Undo", "group": "system", "type": "basic", "code": 122 },
    { "id": "QK_CUT", "label": "Cut", "short": "Cut", "group": "system", "type": "basic", "code": 123 },
    { "id": "QK_COPY", "label": "Copy", "short": "Copy", "group": "system", "type": "basic", "code": 124 },
    { "id": "QK_PASTE", "label": "Paste", "short": "Pst", "group": "system", "type": "basic", "code": 125 },
    { "id": "QK_FIND", "label": "Find", "short": "Find", "group": "system", "type": "basic", "code": 126 },
    { "id": "KC_APP", "label": "App", "short": "App", "group": "system", "type": "basic", "code": 101 },
    { "id": "KC_PWR", "label": "Power", "short": "Pwr", "group": "system", "type": "basic", "code": 165, "aliases": ["SYSTEM_POWER"] },
    { "id": "KC_SLEP", "label": "Sleep", "short": "Slp", "group": "system", "type": "basic", "code": 166, "aliases": ["SYSTEM_SLEEP"] },
    { "id": "KC_WAKE", "label": "Wake", "short": "Wake", "group": "system", "type": "basic", "code": 167, "aliases": ["SYSTEM_WAKE"] },
    { "id": "KC_PSCR", "label": "Print", "short": "Prt", "group": "system", "type": "basic", "code": 70, "aliases": ["PRINT"] },
    { "id": "KC_SLCK", "label": "Scroll", "short": "Scr", "group": "system", "type": "basic", "code": 71, "aliases": ["SCROLL"] },
    { "id": "KC_PAUS", "label": "Pause", "short": "Pus", "group": "system", "type": "basic", "code": 72, "aliases": ["PAUSE"] },
    { "id": "QK_BOOT", "label": "Bootloader", "short": "Boot", "group": "system", "type": "basic", "code": 23552, "requires": ["boot"] },
    { "id": "QK_REBOOT", "label": "Reboot", "short": "Rboot", "group": "system", "type": "basic", "code": 23554, "requires": ["boot"] },
    { "id": "QK_EEPROM_RESET", "label": "EEPROM Reset", "short": "EERst", "group": "system", "type": "basic", "code": 23553, "requires": ["boot"] },
    { "id": "QK_DEBUG", "label": "Debug", "short": "Dbg", "group": "system", "type": "basic", "code": 23568, "requires": ["debug"] },
    { "id": "QK_CLEAR_EEPROM", "label": "Clear EEPROM", "short": "ClrEE", "group": "system", "type": "basic", "code": 60928, "requires": ["boot"] },
    { "id": "QK_MAKE", "label": "Make", "short": "Make", "group": "system", "type": "basic", "code": 23569, "requires": ["debug"] },

    { "id": "QK_MACRO_0", "label": "M0", "short": "M0", "group": "macro", "type": "basic", "code": 24448 },
    { "id": "QK_MACRO_1", "label": "M1", "short": "M1", "group": "macro", "type": "basic", "code": 24449 },
    { "id": "QK_MACRO_2", "label": "M2", "short": "M2", "group": "macro", "type": "basic", "code": 24450 },
    { "id": "QK_MACRO_3", "label": "M3", "short": "M3", "group": "macro", "type": "basic", "code": 24451 },
    { "id": "QK_MACRO_4", "label": "M4", "short": "M4", "group": "macro", "type": "basic", "code": 24452 },
    { "id": "QK_MACRO_5", "label": "M5", "short": "M5", "group": "macro", "type": "basic", "code": 24453 },
    { "id": "QK_MACRO_6", "label": "M6", "short": "M6", "group": "macro", "type": "basic", "code": 24454 },
    { "id": "QK_MACRO_7", "label": "M7", "short": "M7", "group": "macro", "type": "basic", "code": 24455 },
    { "id": "QK_MACRO_8", "label": "M8", "short": "M8", "group": "macro", "type": "basic", "code": 24456 },
    { "id": "QK_MACRO_9", "label": "M9", "short": "M9", "group": "macro", "type": "basic", "code": 24457 },
    { "id": "QK_MACRO_10", "label": "M10", "short": "M10", "group": "macro", "type": "basic", "code": 24458 },
    { "id": "QK_MACRO_11", "label": "M11", "short": "M11", "group": "macro", "type": "basic", "code": 24459 },
    { "id": "QK_MACRO_12", "label": "M12", "short": "M12", "group": "macro", "type": "basic", "code": 24460 },
    { "id": "QK_MACRO_13", "label": "M13", "short": "M13", "group": "macro", "type": "basic", "code": 24461 },
    { "id": "QK_MACRO_14", "label": "M14", "short": "M14", "group": "macro", "type": "basic", "code": 24462 },
    { "id": "QK_MACRO_15", "label": "M15", "short": "M15", "group": "macro", "type": "basic", "code": 24463 },

    { "id": "KC_USER_A0", "label": "User 0xA0", "short": "uA0", "group": "user", "type": "basic", "code": 160 },
    { "id": "KC_USER_A1", "label": "User 0xA1", "short": "uA1", "group": "user", "type": "basic", "code": 161 },
    { "id": "KC_USER_A2", "label": "User 0xA2", "short": "uA2", "group": "user", "type": "basic", "code": 162 },
    { "id": "KC_USER_A3", "label": "User 0xA3", "short": "uA3", "group": "user", "type": "basic", "code": 163 },
    { "id": "KC_USER_A4", "label": "User 0xA4", "short": "uA4", "group": "user", "type": "basic", "code": 164 },
    { "id": "KC_USER_BF", "label": "User 0xBF", "short": "uBF", "group": "user", "type": "basic", "code": 191 },
    { "id": "KC_USER_C0", "label": "User 0xC0", "short": "uC0", "group": "user", "type": "basic", "code": 192 },
    { "id": "KC_USER_C1", "label": "User 0xC1", "short": "uC1", "group": "user", "type": "basic", "code": 193 },
    { "id": "KC_USER_C2", "label": "User 0xC2", "short": "uC2", "group": "user", "type": "basic", "code": 194 },
    { "id": "KC_USER_C3", "label": "User 0xC3", "short": "uC3", "group": "user", "type": "basic", "code": 195 },
    { "id": "KC_USER_C4", "label": "User 0xC4", "short": "uC4", "group": "user", "type": "basic", "code": 196 },
    { "id": "KC_USER_C5", "label": "User 0xC5", "short": "uC5", "group": "user", "type": "basic", "code": 197 },
    { "id": "KC_USER_C6", "label": "User 0xC6", "short": "uC6", "group": "user", "type": "basic", "code": 198 },
    { "id": "KC_USER_C7", "label": "User 0xC7", "short": "uC7", "group": "user", "type": "basic", "code": 199 },
    { "id": "KC_USER_C8", "label": "User 0xC8", "short": "uC8", "group": "user", "type": "basic", "code": 200 },
    { "id": "KC_USER_C9", "label": "User 0xC9", "short": "uC9", "group": "user", "type": "basic", "code": 201 },
    { "id": "KC_USER_CA", "label": "User 0xCA", "short": "uCA", "group": "user", "type": "basic", "code": 202 },
    { "id": "KC_USER_CB", "label": "User 0xCB", "short": "uCB", "group": "user", "type": "basic", "code": 203 },
    { "id": "KC_USER_CC", "label": "User 0xCC", "short": "uCC", "group": "user", "type": "basic", "code": 204 }
  ],
  "mods": {
    "LCTL": 1,
    "LSFT": 2,
    "LALT": 4,
    "LGUI": 8,
    "RCTL": 16,
    "RSFT": 32,
    "RALT": 64,
    "RGUI": 128
  }
}